{"contexts": {"mms-large-1": "ssh://henry@mms-large-1.cs.dartmouth.edu"}, "experiments": [{"name": "0_t5-small_stereoset_classifieronly", "image": "ghcr.io/henryscheible/train:e7dc41f3c035a9669eae132a91f33708414f6f61", "context": "mms-large-1", "card": 0, "buildargs": {"MODEL": "t5-small", "DATASET": "stereoset", "TRAIN_TYPE": "classifieronly", "MODEL_TYPE": "generative", "LEARNING_RATE": 5e-05}}, {"name": "1_t5-small_stereoset_finetuned", "image": "ghcr.io/henryscheible/train:e7dc41f3c035a9669eae132a91f33708414f6f61", "context": "mms-large-1", "card": 1, "buildargs": {"MODEL": "t5-small", "DATASET": "stereoset", "TRAIN_TYPE": "finetuned", "MODEL_TYPE": "generative", "LEARNING_RATE": 5e-05}}, {"name": "2_t5-small_winobias_classifieronly", "image": "ghcr.io/henryscheible/train:e7dc41f3c035a9669eae132a91f33708414f6f61", "context": "mms-large-1", "card": 2, "buildargs": {"MODEL": "t5-small", "DATASET": "winobias", "TRAIN_TYPE": "classifieronly", "MODEL_TYPE": "generative", "LEARNING_RATE": 5e-05}}, {"name": "3_t5-small_winobias_finetuned", "image": "ghcr.io/henryscheible/train:e7dc41f3c035a9669eae132a91f33708414f6f61", "context": "mms-large-1", "card": 3, "buildargs": {"MODEL": "t5-small", "DATASET": "winobias", "TRAIN_TYPE": "finetuned", "MODEL_TYPE": "generative", "LEARNING_RATE": 5e-05}}, {"name": "4_t5-small_crows_pairs_classifieronly", "image": "ghcr.io/henryscheible/train:e7dc41f3c035a9669eae132a91f33708414f6f61", "context": "mms-large-1", "card": 5, "buildargs": {"MODEL": "t5-small", "DATASET": "crows_pairs", "TRAIN_TYPE": "classifieronly", "MODEL_TYPE": "generative", "LEARNING_RATE": 5e-05}}, {"name": "5_t5-small_crows_pairs_finetuned", "image": "ghcr.io/henryscheible/train:e7dc41f3c035a9669eae132a91f33708414f6f61", "context": "mms-large-1", "card": 6, "buildargs": {"MODEL": "t5-small", "DATASET": "crows_pairs", "TRAIN_TYPE": "finetuned", "MODEL_TYPE": "generative", "LEARNING_RATE": 5e-05}}]}